README.rst
setup.py
flask_qcloudsms/__init__.py
flask_qcloudsms.egg-info/PKG-INFO
flask_qcloudsms.egg-info/SOURCES.txt
flask_qcloudsms.egg-info/dependency_links.txt
flask_qcloudsms.egg-info/requires.txt
flask_qcloudsms.egg-info/top_level.txt