Metadata-Version: 1.1
Name: flask-qcloudsms
Version: 0.0.1
Summary: Flask Extension for qcloud sms
Home-page: https://github.com/codeif/flask-qcloudsms
Author: codeif
Author-email: me@codeif.com
License: MIT
Platform: UNKNOWN
Classifier: Programming Language :: Python :: 3
